{
  "annotations": {
    "list": []
  },
  "editable": true,
  "fiscalYearStartMonth": 0,
  "graphTooltip": 1,
  "id": null,
  "links": [],
  "liveNow": true,
  "panels": [
    {
      "gridPos": { "h": 3, "w": 24, "x": 0, "y": 0 },
      "id": 100,
      "options": {
        "content": "# Movie Recommender System - Live Dashboard\n\nReal-time overview of the ML-powered movie recommendation service. This system uses collaborative filtering to suggest personalized movies based on user preferences.",
        "mode": "markdown"
      },
      "title": "",
      "type": "text",
      "transparent": true
    },
    {
      "datasource": { "type": "prometheus", "uid": "prometheus" },
      "fieldConfig": {
        "defaults": {
          "color": { "mode": "thresholds" },
          "mappings": [],
          "thresholds": {
            "mode": "absolute",
            "steps": [
              { "color": "blue", "value": null }
            ]
          },
          "unit": "short"
        }
      },
      "gridPos": { "h": 5, "w": 6, "x": 0, "y": 3 },
      "id": 1,
      "options": {
        "colorMode": "value",
        "graphMode": "area",
        "justifyMode": "auto",
        "orientation": "auto",
        "reduceOptions": { "calcs": ["lastNotNull"], "fields": "", "values": false },
        "textMode": "auto"
      },
      "targets": [
        {
          "expr": "sum(recommend_requests_total)",
          "refId": "A"
        }
      ],
      "title": "Total Recommendations",
      "type": "stat"
    },
    {
      "datasource": { "type": "prometheus", "uid": "prometheus" },
      "fieldConfig": {
        "defaults": {
          "color": { "mode": "thresholds" },
          "mappings": [],
          "thresholds": {
            "mode": "absolute",
            "steps": [
              { "color": "green", "value": null },
              { "color": "yellow", "value": 50 },
              { "color": "red", "value": 100 }
            ]
          },
          "unit": "ms"
        }
      },
      "gridPos": { "h": 5, "w": 6, "x": 6, "y": 3 },
      "id": 2,
      "options": {
        "colorMode": "value",
        "graphMode": "area",
        "justifyMode": "auto",
        "orientation": "auto",
        "reduceOptions": { "calcs": ["lastNotNull"], "fields": "", "values": false },
        "textMode": "auto"
      },
      "targets": [
        {
          "expr": "(sum(recommend_latency_seconds_sum) / sum(recommend_latency_seconds_count)) * 1000",
          "refId": "A"
        }
      ],
      "title": "Avg Response Time",
      "type": "stat"
    },
    {
      "datasource": { "type": "prometheus", "uid": "prometheus" },
      "fieldConfig": {
        "defaults": {
          "color": { "mode": "thresholds" },
          "mappings": [],
          "thresholds": {
            "mode": "absolute",
            "steps": [
              { "color": "green", "value": null },
              { "color": "yellow", "value": 0.01 },
              { "color": "red", "value": 0.05 }
            ]
          },
          "unit": "percentunit"
        }
      },
      "gridPos": { "h": 5, "w": 6, "x": 12, "y": 3 },
      "id": 3,
      "options": {
        "colorMode": "value",
        "graphMode": "area",
        "justifyMode": "auto",
        "orientation": "auto",
        "reduceOptions": { "calcs": ["lastNotNull"], "fields": "", "values": false },
        "textMode": "auto"
      },
      "targets": [
        {
          "expr": "sum(recommend_requests_total{status!=\"200\"}) / sum(recommend_requests_total) or vector(0)",
          "refId": "A"
        }
      ],
      "title": "Error Rate",
      "type": "stat"
    },
    {
      "datasource": { "type": "prometheus", "uid": "prometheus" },
      "fieldConfig": {
        "defaults": {
          "color": { "mode": "thresholds" },
          "mappings": [
            { "options": { "1": { "color": "green", "index": 0, "text": "ONLINE" } }, "type": "value" },
            { "options": { "match": "null", "result": { "color": "red", "index": 1, "text": "OFFLINE" } }, "type": "special" }
          ],
          "thresholds": {
            "mode": "absolute",
            "steps": [
              { "color": "red", "value": null },
              { "color": "green", "value": 1 }
            ]
          }
        }
      },
      "gridPos": { "h": 5, "w": 6, "x": 18, "y": 3 },
      "id": 4,
      "options": {
        "colorMode": "background",
        "graphMode": "none",
        "justifyMode": "auto",
        "orientation": "auto",
        "reduceOptions": { "calcs": ["lastNotNull"], "fields": "", "values": false },
        "textMode": "auto"
      },
      "targets": [
        {
          "expr": "up{job=\"movie-recommender-local\"}",
          "refId": "A"
        }
      ],
      "title": "System Status",
      "type": "stat"
    },
    {
      "datasource": { "type": "prometheus", "uid": "prometheus" },
      "fieldConfig": {
        "defaults": {
          "color": { "mode": "palette-classic" },
          "custom": {
            "axisCenteredZero": false,
            "axisColorMode": "text",
            "axisLabel": "",
            "axisPlacement": "auto",
            "barAlignment": 0,
            "drawStyle": "line",
            "fillOpacity": 20,
            "gradientMode": "opacity",
            "hideFrom": { "legend": false, "tooltip": false, "viz": false },
            "lineInterpolation": "smooth",
            "lineWidth": 2,
            "pointSize": 5,
            "scaleDistribution": { "type": "linear" },
            "showPoints": "auto",
            "spanNulls": false,
            "stacking": { "group": "A", "mode": "none" },
            "thresholdsStyle": { "mode": "off" }
          },
          "mappings": [],
          "thresholds": { "mode": "absolute", "steps": [{ "color": "green", "value": null }] },
          "unit": "short"
        }
      },
      "gridPos": { "h": 8, "w": 12, "x": 0, "y": 8 },
      "id": 5,
      "options": {
        "legend": { "calcs": ["mean", "max"], "displayMode": "table", "placement": "bottom", "showLegend": true },
        "tooltip": { "mode": "multi", "sort": "desc" }
      },
      "targets": [
        {
          "expr": "sum(increase(recommend_requests_total[1m]))",
          "legendFormat": "Requests/min",
          "refId": "A"
        }
      ],
      "title": "Recommendation Traffic",
      "type": "timeseries"
    },
    {
      "datasource": { "type": "prometheus", "uid": "prometheus" },
      "fieldConfig": {
        "defaults": {
          "color": { "mode": "palette-classic" },
          "custom": {
            "axisCenteredZero": false,
            "axisColorMode": "text",
            "axisLabel": "",
            "axisPlacement": "auto",
            "barAlignment": 0,
            "drawStyle": "line",
            "fillOpacity": 10,
            "gradientMode": "opacity",
            "hideFrom": { "legend": false, "tooltip": false, "viz": false },
            "lineInterpolation": "smooth",
            "lineWidth": 2,
            "pointSize": 5,
            "scaleDistribution": { "type": "linear" },
            "showPoints": "auto",
            "spanNulls": false,
            "stacking": { "group": "A", "mode": "none" },
            "thresholdsStyle": { "mode": "line" }
          },
          "mappings": [],
          "thresholds": { "mode": "absolute", "steps": [{ "color": "green", "value": null }, { "color": "red", "value": 100 }] },
          "unit": "ms"
        }
      },
      "gridPos": { "h": 8, "w": 12, "x": 12, "y": 8 },
      "id": 6,
      "options": {
        "legend": { "calcs": ["mean", "max", "last"], "displayMode": "table", "placement": "bottom", "showLegend": true },
        "tooltip": { "mode": "multi", "sort": "desc" }
      },
      "targets": [
        {
          "expr": "(sum(increase(recommend_latency_seconds_sum[1m])) / sum(increase(recommend_latency_seconds_count[1m]))) * 1000",
          "legendFormat": "Avg Latency",
          "refId": "A"
        }
      ],
      "title": "Response Time",
      "type": "timeseries"
    },
    {
      "gridPos": { "h": 2, "w": 24, "x": 0, "y": 16 },
      "id": 101,
      "options": {
        "content": "## Model Information",
        "mode": "markdown"
      },
      "title": "",
      "type": "text",
      "transparent": true
    },
    {
      "datasource": { "type": "prometheus", "uid": "prometheus" },
      "fieldConfig": {
        "defaults": {
          "color": { "mode": "thresholds" },
          "mappings": [],
          "thresholds": { "mode": "absolute", "steps": [{ "color": "purple", "value": null }] }
        }
      },
      "gridPos": { "h": 4, "w": 6, "x": 0, "y": 18 },
      "id": 7,
      "options": {
        "colorMode": "none",
        "graphMode": "none",
        "justifyMode": "auto",
        "orientation": "auto",
        "reduceOptions": { "calcs": ["lastNotNull"], "fields": "", "values": false },
        "textMode": "name"
      },
      "targets": [
        {
          "expr": "model_version_info{job=\"movie-recommender-local\"}",
          "legendFormat": "{{model_name}}",
          "refId": "A"
        }
      ],
      "title": "Model Type",
      "type": "stat"
    },
    {
      "datasource": { "type": "prometheus", "uid": "prometheus" },
      "fieldConfig": {
        "defaults": {
          "color": { "mode": "thresholds" },
          "mappings": [],
          "thresholds": { "mode": "absolute", "steps": [{ "color": "orange", "value": null }] }
        }
      },
      "gridPos": { "h": 4, "w": 6, "x": 6, "y": 18 },
      "id": 8,
      "options": {
        "colorMode": "none",
        "graphMode": "none",
        "justifyMode": "auto",
        "orientation": "auto",
        "reduceOptions": { "calcs": ["lastNotNull"], "fields": "", "values": false },
        "textMode": "name"
      },
      "targets": [
        {
          "expr": "model_version_info{job=\"movie-recommender-local\"}",
          "legendFormat": "{{version}}",
          "refId": "A"
        }
      ],
      "title": "Model Version",
      "type": "stat"
    },
    {
      "datasource": { "type": "prometheus", "uid": "prometheus" },
      "fieldConfig": {
        "defaults": {
          "color": { "mode": "thresholds" },
          "mappings": [],
          "thresholds": { "mode": "absolute", "steps": [{ "color": "blue", "value": null }] },
          "unit": "short"
        }
      },
      "gridPos": { "h": 4, "w": 6, "x": 12, "y": 18 },
      "id": 9,
      "options": {
        "colorMode": "value",
        "graphMode": "area",
        "justifyMode": "auto",
        "orientation": "auto",
        "reduceOptions": { "calcs": ["lastNotNull"], "fields": "", "values": false },
        "textMode": "auto"
      },
      "targets": [
        {
          "expr": "sum(feature_retrieval_total)",
          "refId": "A"
        }
      ],
      "title": "Feature Lookups",
      "type": "stat"
    },
    {
      "datasource": { "type": "prometheus", "uid": "prometheus" },
      "fieldConfig": {
        "defaults": {
          "color": { "mode": "thresholds" },
          "mappings": [],
          "thresholds": { "mode": "absolute", "steps": [{ "color": "green", "value": null }] },
          "unit": "ms"
        }
      },
      "gridPos": { "h": 4, "w": 6, "x": 18, "y": 18 },
      "id": 10,
      "options": {
        "colorMode": "value",
        "graphMode": "area",
        "justifyMode": "auto",
        "orientation": "auto",
        "reduceOptions": { "calcs": ["lastNotNull"], "fields": "", "values": false },
        "textMode": "auto"
      },
      "targets": [
        {
          "expr": "(sum(feature_retrieval_latency_seconds_sum) / sum(feature_retrieval_latency_seconds_count)) * 1000",
          "refId": "A"
        }
      ],
      "title": "Avg Feature Latency",
      "type": "stat"
    },
    {
      "gridPos": { "h": 3, "w": 24, "x": 0, "y": 22 },
      "id": 102,
      "options": {
        "content": "## How It Works\n\n**1. User Request** - User asks for movie recommendations via API | **2. Feature Lookup** - System retrieves user preferences from Feature Store (Feast) | **3. Model Inference** - ALS/NCF model generates personalized recommendations | **4. Response** - Top-K movies returned with titles and confidence scores | **5. Logging** - Request logged to Kafka for continuous learning",
        "mode": "markdown"
      },
      "title": "",
      "type": "text",
      "transparent": true
    }
  ],
  "refresh": "5s",
  "schemaVersion": 38,
  "style": "dark",
  "tags": ["overview", "business", "movie-recommender"],
  "templating": { "list": [] },
  "time": { "from": "now-1h", "to": "now" },
  "timepicker": {},
  "timezone": "browser",
  "title": "Movie Recommender - Business Overview",
  "uid": "movie-recs-overview",
  "version": 1,
  "weekStart": ""
}
